Metadata-Version: 2.4
Name: anvil-parser-modern
Version: 0.10.0
Summary: A Minecraft anvil file format parser
Author: voidfemme
License-Expression: MIT
Project-URL: Homepage, https://github.com/voidfemme/anvil-parser
Project-URL: Repository, https://github.com/voidfemme/anvil-parser
Project-URL: Issues, https://github.com/voidfemme/anvil-parser/issues
Keywords: minecraft,anvil,mca,region,chunk,nbt
Classifier: Development Status :: 4 - Beta
Classifier: Intended Audience :: Developers
Classifier: Programming Language :: Python :: 3
Classifier: Programming Language :: Python :: 3.10
Classifier: Programming Language :: Python :: 3.11
Classifier: Programming Language :: Python :: 3.12
Classifier: Programming Language :: Python :: 3.13
Classifier: Operating System :: OS Independent
Classifier: Topic :: Games/Entertainment
Classifier: Topic :: Software Development :: Libraries :: Python Modules
Requires-Python: >=3.10
License-File: LICENSE
Requires-Dist: NBT>=1.5.1
Requires-Dist: frozendict>=2.3.0
Provides-Extra: dev
Requires-Dist: pytest>=6.0.0; extra == "dev"
Requires-Dist: sphinx>=8.0.0; extra == "dev"
Requires-Dist: sphinx-autodoc-typehints>=1.10.3; extra == "dev"
Requires-Dist: sphinxcontrib-trio>=1.1.0; extra == "dev"
Dynamic: license-file
